{
  "project_info": {
    "project_number": "802038647784",
    "project_id": "chatting-app-flutter-4c092",
    "storage_bucket": "chatting-app-flutter-4c092.firebasestorage.app"
  },
  "client": [
    {
      "client_info": {
        "mobilesdk_app_id": "1:802038647784:android:15790a0c509458ac74725d",
        "android_client_info": {
          "package_name": "com.example.firebase_session"
        }
      },
      "oauth_client": [],
      "api_key": [
        {
          "current_key": "AIzaSyCsw9_W7JIDcBcOU4qUO41S9FqDsZeoLro"
        }
      ],
      "services": {
        "appinvite_service": {
          "other_platform_oauth_client": []
        }
      }
    }
  ],
  "configuration_version": "1"
}